pytest_modified_env/__init__.py
pytest_modified_env/plugin.py
pytest_modified_env/py.typed
pytest_modified_env-0.1.0.dist-info/entry_points.txt
pytest_modified_env-0.1.0.dist-info/LICENSE
pytest_modified_env-0.1.0.dist-info/WHEEL
pytest_modified_env-0.1.0.dist-info/METADATA
pytest_modified_env-0.1.0.dist-info/RECORD
