Metadata-Version: 2.1
Name: pytest-modified-env
Version: 0.1.0
Summary: Pytest plugin to fail a test if it leaves modified `os.environ` afterwards.
Home-page: https://github.com/wemake-services/pytest-modified-env
License: MIT
Keywords: pytest,pytest-plugin,os.environ,testing,unittest,tests,test,unit tests,code quality
Author: Nikita Sobolev
Author-email: mail@sobolevn.me
Requires-Python: >=3.7,<4.0
Classifier: Development Status :: 4 - Beta
Classifier: Intended Audience :: Developers
Classifier: License :: OSI Approved :: MIT License
Classifier: Operating System :: OS Independent
Classifier: Programming Language :: Python :: 3
Classifier: Programming Language :: Python :: 3.10
Classifier: Programming Language :: Python :: 3.7
Classifier: Programming Language :: Python :: 3.8
Classifier: Programming Language :: Python :: 3.9
Classifier: Topic :: Software Development :: Libraries :: Python Modules
Project-URL: Funding, https://github.com/sponsors/wemake-services
Project-URL: Repository, https://github.com/wemake-services/pytest-modified-env
